frozen_field/__init__.py
frozen_field/apps.py
frozen_field/exceptions.py
frozen_field/fields.py
frozen_field/models.py
frozen_field/serializers.py
frozen_field/settings.py
frozen_field/types.py
django_frozen_field-0.1.1.dist-info/LICENSE
django_frozen_field-0.1.1.dist-info/WHEEL
django_frozen_field-0.1.1.dist-info/METADATA
django_frozen_field-0.1.1.dist-info/RECORD
